camel_downloader/__init__.py
camel_downloader/main.py
cameldownloader-2.0.0.dist-info/METADATA
cameldownloader-2.0.0.dist-info/WHEEL
cameldownloader-2.0.0.dist-info/entry_points.txt
cameldownloader-2.0.0.dist-info/top_level.txt
cameldownloader-2.0.0.dist-info/RECORD
